{"name":"t343-vedelmi-vonal","posts":[{"name":"Stephanus Tavilrond","content":"Az eg&#xE9;sz k&#xF6;zs&#xE9;get egy hatalmas faker&#xED;t&#xE9;s veszi k&#xF6;r&#xFC;l. A kapukn&#xE1;l pedig &#x151;rb&#xF3;d&#xE9;k tal&#xE1;lhat&#xF3;ak. Mivel az eg&#xE9;sz k&#xF6;zs&#xE9;get csak 120 f&#xE9;lszerzet lakja, mindig n&#xE9;gy kiv&#xE1;lasztott &#xE9;s kik&#xE9;pzett f&#xE9;lszerzetet &#xE1;ll&#xED;tanak az &#xF6;sszes kapuhoz. Kett&#x151; a kapukn&#xE1;l &#x151;rk&#xF6;dik, kett&#x151; meg a t&#xE1;voli t&#xE1;jat k&#xE9;mleli egy feler&#x151;s&#xED;tett &#xE1;ll&#xE1;sb&#xF3;l.","date":"Pént. Május 21, 2010 9:28 am"}]}