{"name":"t42-k-o-s-z-a","posts":[{"name":"Stephanus Tavilrond","content":"<img src=\"https://redcdn.net/ihimizer/img3/3580/archeru.jpg\" border=\"0\" alt=\"K &#xF3; s z a Archeru\"><br><br><span style=\"font-size: 24px; line-height: normal\"><strong>K&#xF3;sza</strong></span><br><br><img src=\"https://2img.net/h/i193.photobucket.com/albums/z119/Sandro_042/ranger.png\" border=\"0\" alt=\"K &#xF3; s z a Ranger\"><br><br><u><strong>Sz&#xFC;ks&#xE9;ges jellem:</strong></u><br>-Semleges J&#xF3;<br>-Kaotikus J&#xF3;<br><u><strong>Sz&#xFC;ks&#xE9;ges kaszt:</strong></u> Du&#xE1;lkaszt Harcos-Druida VAGY Du&#xE1;lkaszt Tolvaj-Druida<br><u><strong>Sz&#xFC;ks&#xE9;ge faj:</strong></u> Ember, Erd&#x151;elf, F&#xE9;l-elf, F&#xE9;l-ork (m&#xE1;s is lehet, de akkor j&#xF3;l ki kell magyar&#xE1;znod)<br><br><u><strong>B&#xF3;nusz k&#xE9;pess&#xE9;g(ek):</strong></u><br>-Elvar&#xE1;zsolt &#xED;j: K&#xE9;pes egy &#xE1;tokkal vagy egy puszt&#xED;t&#xF3; (t&#xE1;mad&#xF3;) var&#xE1;zslattal kombin&#xE1;lva az &#xED;j&#xE1;t, ez&#xE1;ltal a kil&#x151;tt &#xED;jvessz&#x151;i a megsebzett &#xE1;ldozatot el&#xE1;tkozz&#xE1;k vagy m&#xE9;gjobban sebzik (pl. ha egy t&#x171;zvar&#xE1;zslattal kombin&#xE1;ltad akkor a ny&#xED;lvessz&#x151; el&#xE9;geti az &#xE1;ldozatot)<br>-Alapvet&#x151; Kardforgat&#xE1;s (ha m&#xE9;g nem rendelkezik vele)<br>-Halad&#xF3; Kardforgat&#xE1;s<br>-Alapvet&#x151; &#xCD;j haszn&#xE1;lat (ha m&#xE9;g nem rendelkezik vele)<br>-Halad&#xF3; &#xCD;j haszn&#xE1;lat<br>-Alapvet&#x151; Nyomk&#xF6;vet&#xE9;s (ha m&#xE9;g nem rendelkezik vele)<br>-Alapvet&#x151; Lopakod&#xE1;s (ha m&#xE9;g nem rendelkezik vele)<br>-Alapvet&#x151; Term&#xE9;szetismeret<br><br><br><strong>FONTOS!</strong> <br>1. Amikor k&#xF3;sz&#xE1;v&#xE1; v&#xE1;lsz, elveszted a K&#xF6;zepes &#xE9;s Neh&#xE9;z P&#xE1;nc&#xE9;livsel&#xE9;s k&#xE9;pess&#xE9;geidet. &#xC9;s am&#xED;g k&#xF3;sza vagy, nem viselhetsz k&#xF6;zepes vagy neh&#xE9;z p&#xE1;nc&#xE9;lt.<br>2.Ha egy k&#xF3;sza let&#xE9;r a f&#xE9;ny &#xFA;tj&#xE1;r&#xF3;l, akkor...<br>-Elvesz&#xED;ti a k&#xE9;pess&#xE9;geit<br>-Elvesz&#xED;ti a K&#xF3;sza preszt&#xED;zs oszt&#xE1;lyt, &#xE9;s egyszer&#x171; Harcos-Druid&#xE1;v&#xE1; vagy Tolvaj-Druid&#xE1;v&#xE1; avanzs&#xE1;l&#xF3;dik. Rosszabb esetben m&#xE1;r nem is druida t&#xF6;bb&#xE9;, hanem s&#xF6;t&#xE9;t Var&#xE1;zsl&#xF3;.<br>-A jelleme Semleges J&#xF3;r&#xF3;l vagy Kaotikus J&#xF3;r&#xF3;l &#xE1;tmegy valamilyen Gonoszba vagy Kaotikusba, de semmik&#xE9;pp sem lehet J&#xF3;.<br>-Megkapja a K&#xF6;zepes &#xE9;s Neh&#xE9;z P&#xE1;nc&#xE9;lvisel&#xE9;s k&#xE9;pzetts&#xE9;geket<br><br><br><u><strong>Leir&#xE1;s</strong></u><br><br>A k&#xF3;sz&#xE1;k egy t&#xF6;k&#xE9;letes &#xE1;tmenet a druida &#xE9;s a harcos/tolvaj k&#xF6;z&#xF6;tt. Sz&#xFC;letett kalandorok, az erd&#x151;k igazi ismer&#x151;i, az utak &#xE1;lland&#xF3; j&#xE1;r&#xF3;i.<br>A k&#xF3;sz&#xE1;k lehetnek az elfek erd&#x151;inek v&#xE9;delmez&#x151; harcosai, de ak&#xE1;r a legjobb k&#xE9;mek, nyomoz&#xF3;k is. <br>Minden k&#xE9;pess&#xE9;ggek rendelkeznek amivel a druid&#xE1;k rendelkeznek.<br><br>Egyesek a lovagokhoz hasonl&#xED;tj&#xE1;k &#x151;ket.","date":"Pént. Ápr. 02, 2010 10:30 am"}]}